{
  "sample_idx": 184,
  "seed": 20260804,
  "family": "safe_long_forward",
  "adv": {
    "tail_type": "conv_tail",
    "wing_position": 0.459,
    "tail_position": 0.926,
    "length": 1365.0,
    "max_width": 110.08,
    "max_height": 106.12,
    "wingspan": 1937.0,
    "wing_height_ratio": 0.586,
    "design_name": "blended",
    "wall_thickness": 6.77,
    "end_cap_percent": 0.033,
    "aspect_ratio": 8.62,
    "taper": 0.465,
    "sweep": 18.11,
    "dihedral": 9.76,
    "twist": 3.07,
    "root_incidence": -1.67,
    "airfoil_source": "naca_4",
    "root_naca_code": "2410",
    "tip_naca_code": "2412",
    "root_csv_filepath": null,
    "tip_csv_filepath": null,
    "v_tail_angle": 0.0,
    "hstab_semispan": 205.0,
    "hstab_aspect_ratio": 3.49,
    "hstab_taper": 0.447,
    "hstab_sweep": 29.59,
    "hstab_dihedral": 5.13,
    "hstab_root_incidence": -3.65,
    "hstab_airfoil_source": "naca_4",
    "hstab_root_naca_code": "0012",
    "hstab_tip_naca_code": "0008",
    "hstab_root_csv_filepath": null,
    "hstab_tip_csv_filepath": null,
    "vstab_height": 143.64,
    "vstab_aspect_ratio": 1.3,
    "vstab_taper": 0.58,
    "vstab_sweep": 18.26,
    "vstab_airfoil_source": "naca_4",
    "vstab_root_naca_code": "0012",
    "vstab_tip_naca_code": "0008",
    "vstab_root_csv_filepath": null,
    "vstab_tip_csv_filepath": null
  }
}
