{
  "sample_idx": 14284,
  "seed": 20274904,
  "family": "conv_tail_wide",
  "adv": {
    "tail_type": "conv_tail",
    "length": 1075.0,
    "max_width": 132.95,
    "max_height": 125.38,
    "wingspan": 1980.0,
    "wing_position": 0.408,
    "wing_height_ratio": 0.5,
    "tail_position": 0.862,
    "design_name": "transport",
    "wall_thickness": 6.23,
    "end_cap_percent": 0.033,
    "aspect_ratio": 6.8,
    "taper": 0.479,
    "sweep": 15.93,
    "dihedral": 4.86,
    "twist": 2.42,
    "root_incidence": 1.45,
    "airfoil_source": "naca_4",
    "root_naca_code": "0012",
    "tip_naca_code": "0009",
    "root_csv_filepath": null,
    "tip_csv_filepath": null,
    "v_tail_angle": 0.0,
    "hstab_semispan": 286.0,
    "hstab_aspect_ratio": 4.77,
    "hstab_taper": 0.477,
    "hstab_sweep": 26.71,
    "hstab_dihedral": 6.82,
    "hstab_root_incidence": 1.19,
    "hstab_airfoil_source": "naca_4",
    "hstab_root_naca_code": "0012",
    "hstab_tip_naca_code": "0008",
    "hstab_root_csv_filepath": null,
    "hstab_tip_csv_filepath": null,
    "vstab_height": 206.94,
    "vstab_aspect_ratio": 2.08,
    "vstab_taper": 0.39,
    "vstab_sweep": 35.82,
    "vstab_airfoil_source": "naca_4",
    "vstab_root_naca_code": "0012",
    "vstab_tip_naca_code": "0008",
    "vstab_root_csv_filepath": null,
    "vstab_tip_csv_filepath": null
  }
}
