{
  "sample_idx": 16674,
  "seed": 20277294,
  "family": "extreme_wide_frontier",
  "adv": {
    "wing_position": 0.48,
    "tail_position": 0.77,
    "length": 1551.0,
    "wingspan": 1305.0,
    "aspect_ratio": 4.83,
    "taper": 0.419,
    "sweep": 6.96,
    "dihedral": 10.22,
    "twist": 1.23,
    "root_incidence": 2.06,
    "wing_height_ratio": 0.588,
    "max_width": 213.24,
    "max_height": 79.19,
    "wall_thickness": 7.99,
    "end_cap_percent": 0.091,
    "hstab_semispan": 352.0,
    "hstab_aspect_ratio": 6.28,
    "hstab_taper": 0.408,
    "hstab_sweep": 36.8,
    "hstab_dihedral": 8.3,
    "hstab_root_incidence": -7.2,
    "vstab_height": 96.0,
    "vstab_aspect_ratio": 2.21,
    "vstab_taper": 0.498,
    "vstab_sweep": 48.96,
    "design_name": "simple",
    "airfoil_source": "naca_4",
    "root_naca_code": "2410",
    "tip_naca_code": "0009",
    "root_csv_filepath": null,
    "tip_csv_filepath": null,
    "tail_type": "conv_tail",
    "v_tail_angle": 0.0,
    "hstab_airfoil_source": "naca_4",
    "hstab_root_naca_code": "0012",
    "hstab_tip_naca_code": "0008",
    "hstab_root_csv_filepath": null,
    "hstab_tip_csv_filepath": null,
    "vstab_airfoil_source": "naca_4",
    "vstab_root_naca_code": "0012",
    "vstab_tip_naca_code": "0008",
    "vstab_root_csv_filepath": null,
    "vstab_tip_csv_filepath": null
  }
}
