{
  "sample_idx": 17853,
  "seed": 20278473,
  "family": "conv_tail_wide",
  "adv": {
    "tail_type": "conv_tail",
    "length": 1327.0,
    "max_width": 152.65,
    "max_height": 113.58,
    "wingspan": 1462.0,
    "wing_position": 0.643,
    "wing_height_ratio": 0.381,
    "tail_position": 0.934,
    "design_name": "blended",
    "wall_thickness": 5.59,
    "end_cap_percent": 0.047,
    "aspect_ratio": 7.9,
    "taper": 0.514,
    "sweep": 24.48,
    "dihedral": 6.78,
    "twist": 1.4,
    "root_incidence": -0.55,
    "airfoil_source": "naca_4",
    "root_naca_code": "2410",
    "tip_naca_code": "2412",
    "root_csv_filepath": null,
    "tip_csv_filepath": null,
    "v_tail_angle": 0.0,
    "hstab_semispan": 321.0,
    "hstab_aspect_ratio": 4.48,
    "hstab_taper": 0.404,
    "hstab_sweep": 24.42,
    "hstab_dihedral": 7.09,
    "hstab_root_incidence": -3.92,
    "hstab_airfoil_source": "naca_4",
    "hstab_root_naca_code": "0012",
    "hstab_tip_naca_code": "0008",
    "hstab_root_csv_filepath": null,
    "hstab_tip_csv_filepath": null,
    "vstab_height": 226.19,
    "vstab_aspect_ratio": 1.52,
    "vstab_taper": 0.41,
    "vstab_sweep": 32.58,
    "vstab_airfoil_source": "naca_4",
    "vstab_root_naca_code": "0012",
    "vstab_tip_naca_code": "0008",
    "vstab_root_csv_filepath": null,
    "vstab_tip_csv_filepath": null
  }
}
