{
  "sample_idx": 19042,
  "seed": 20279662,
  "family": "v_tail_wide",
  "adv": {
    "tail_type": "v_tail",
    "length": 1016.0,
    "max_width": 148.77,
    "max_height": 92.06,
    "wingspan": 1215.0,
    "wing_position": 0.673,
    "wing_height_ratio": 0.485,
    "tail_position": 0.852,
    "design_name": "blended",
    "wall_thickness": 6.26,
    "end_cap_percent": 0.037,
    "aspect_ratio": 5.61,
    "taper": 0.406,
    "sweep": 21.87,
    "dihedral": 1.84,
    "twist": 2.24,
    "root_incidence": 0.55,
    "airfoil_source": "naca_4",
    "root_naca_code": "2410",
    "tip_naca_code": "0009",
    "root_csv_filepath": null,
    "tip_csv_filepath": null,
    "v_tail_angle": 114.9,
    "hstab_semispan": 233.0,
    "hstab_aspect_ratio": 3.89,
    "hstab_taper": 0.393,
    "hstab_sweep": 29.99,
    "hstab_dihedral": 5.54,
    "hstab_root_incidence": -4.22,
    "hstab_airfoil_source": "naca_4",
    "hstab_root_naca_code": "0012",
    "hstab_tip_naca_code": "0008",
    "hstab_root_csv_filepath": null,
    "hstab_tip_csv_filepath": null,
    "vstab_height": 199.16,
    "vstab_aspect_ratio": 1.8,
    "vstab_taper": 0.4,
    "vstab_sweep": 39.59,
    "vstab_airfoil_source": "naca_4",
    "vstab_root_naca_code": "0012",
    "vstab_tip_naca_code": "0008",
    "vstab_root_csv_filepath": null,
    "vstab_tip_csv_filepath": null
  }
}
