{
  "sample_idx": 20137,
  "seed": 20280757,
  "family": "conv_tail_wide",
  "adv": {
    "tail_type": "conv_tail",
    "length": 867.0,
    "max_width": 193.93,
    "max_height": 86.93,
    "wingspan": 1880.0,
    "wing_position": 0.437,
    "wing_height_ratio": 0.596,
    "tail_position": 0.899,
    "design_name": "transport",
    "wall_thickness": 5.92,
    "end_cap_percent": 0.058,
    "aspect_ratio": 10.57,
    "taper": 0.433,
    "sweep": 19.7,
    "dihedral": 9.66,
    "twist": 2.39,
    "root_incidence": 4.24,
    "airfoil_source": "naca_4",
    "root_naca_code": "2410",
    "tip_naca_code": "2412",
    "root_csv_filepath": null,
    "tip_csv_filepath": null,
    "v_tail_angle": 0.0,
    "hstab_semispan": 309.0,
    "hstab_aspect_ratio": 3.22,
    "hstab_taper": 0.537,
    "hstab_sweep": 20.98,
    "hstab_dihedral": 7.44,
    "hstab_root_incidence": -4.1,
    "hstab_airfoil_source": "naca_4",
    "hstab_root_naca_code": "0012",
    "hstab_tip_naca_code": "0008",
    "hstab_root_csv_filepath": null,
    "hstab_tip_csv_filepath": null,
    "vstab_height": 224.45,
    "vstab_aspect_ratio": 1.78,
    "vstab_taper": 0.62,
    "vstab_sweep": 21.36,
    "vstab_airfoil_source": "naca_4",
    "vstab_root_naca_code": "0012",
    "vstab_tip_naca_code": "0008",
    "vstab_root_csv_filepath": null,
    "vstab_tip_csv_filepath": null
  }
}
