{
  "sample_idx": 21921,
  "seed": 20282541,
  "family": "extreme_wide_frontier",
  "adv": {
    "wing_position": 0.69,
    "tail_position": 0.858,
    "length": 1079.0,
    "wingspan": 1989.0,
    "aspect_ratio": 10.82,
    "taper": 0.386,
    "sweep": 15.3,
    "dihedral": 0.51,
    "twist": 5.61,
    "root_incidence": 3.98,
    "wing_height_ratio": 0.467,
    "max_width": 186.62,
    "max_height": 74.96,
    "wall_thickness": 6.78,
    "end_cap_percent": 0.05,
    "hstab_semispan": 203.0,
    "hstab_aspect_ratio": 3.02,
    "hstab_taper": 0.372,
    "hstab_sweep": 19.68,
    "hstab_dihedral": 10.85,
    "hstab_root_incidence": -3.98,
    "vstab_height": 213.0,
    "vstab_aspect_ratio": 1.91,
    "vstab_taper": 0.682,
    "vstab_sweep": 25.32,
    "design_name": "racing",
    "airfoil_source": "naca_4",
    "root_naca_code": "2412",
    "tip_naca_code": "2412",
    "root_csv_filepath": null,
    "tip_csv_filepath": null,
    "tail_type": "v_tail",
    "v_tail_angle": 122.7,
    "hstab_airfoil_source": "naca_4",
    "hstab_root_naca_code": "0012",
    "hstab_tip_naca_code": "0008",
    "hstab_root_csv_filepath": null,
    "hstab_tip_csv_filepath": null,
    "vstab_airfoil_source": "naca_4",
    "vstab_root_naca_code": "0012",
    "vstab_tip_naca_code": "0008",
    "vstab_root_csv_filepath": null,
    "vstab_tip_csv_filepath": null
  }
}
