{
  "sample_idx": 23379,
  "seed": 20283999,
  "family": "large_hstab_wide",
  "adv": {
    "tail_type": "conv_tail",
    "hstab_semispan": 304.0,
    "hstab_aspect_ratio": 2.65,
    "length": 1194.0,
    "max_width": 199.65,
    "max_height": 138.28,
    "wingspan": 1732.0,
    "wing_position": 0.411,
    "wing_height_ratio": 0.613,
    "tail_position": 0.904,
    "design_name": "racing",
    "wall_thickness": 3.64,
    "end_cap_percent": 0.067,
    "aspect_ratio": 10.25,
    "taper": 0.364,
    "sweep": 17.66,
    "dihedral": 5.93,
    "twist": 1.93,
    "root_incidence": 0.94,
    "airfoil_source": "naca_4",
    "root_naca_code": "0012",
    "tip_naca_code": "2408",
    "root_csv_filepath": null,
    "tip_csv_filepath": null,
    "v_tail_angle": 0.0,
    "hstab_taper": 0.434,
    "hstab_sweep": 28.94,
    "hstab_dihedral": 7.0,
    "hstab_root_incidence": 0.42,
    "hstab_airfoil_source": "naca_4",
    "hstab_root_naca_code": "0012",
    "hstab_tip_naca_code": "0008",
    "hstab_root_csv_filepath": null,
    "hstab_tip_csv_filepath": null,
    "vstab_height": 129.42,
    "vstab_aspect_ratio": 1.16,
    "vstab_taper": 0.55,
    "vstab_sweep": 21.75,
    "vstab_airfoil_source": "naca_4",
    "vstab_root_naca_code": "0012",
    "vstab_tip_naca_code": "0008",
    "vstab_root_csv_filepath": null,
    "vstab_tip_csv_filepath": null
  }
}
