{
  "sample_idx": 25066,
  "seed": 20285686,
  "family": "extreme_wide_frontier",
  "adv": {
    "wing_position": 0.573,
    "tail_position": 0.902,
    "length": 1265.0,
    "wingspan": 1410.0,
    "aspect_ratio": 11.11,
    "taper": 0.486,
    "sweep": 30.23,
    "dihedral": 5.72,
    "twist": 0.14,
    "root_incidence": -2.43,
    "wing_height_ratio": 0.316,
    "max_width": 87.23,
    "max_height": 141.76,
    "wall_thickness": 6.96,
    "end_cap_percent": 0.11,
    "hstab_semispan": 403.0,
    "hstab_aspect_ratio": 5.67,
    "hstab_taper": 0.67,
    "hstab_sweep": 27.87,
    "hstab_dihedral": 7.99,
    "hstab_root_incidence": 3.06,
    "vstab_height": 107.0,
    "vstab_aspect_ratio": 2.03,
    "vstab_taper": 0.726,
    "vstab_sweep": 47.29,
    "design_name": "racing",
    "airfoil_source": "naca_4",
    "root_naca_code": "2410",
    "tip_naca_code": "0009",
    "root_csv_filepath": null,
    "tip_csv_filepath": null,
    "tail_type": "conv_tail",
    "v_tail_angle": 0.0,
    "hstab_airfoil_source": "naca_4",
    "hstab_root_naca_code": "0012",
    "hstab_tip_naca_code": "0008",
    "hstab_root_csv_filepath": null,
    "hstab_tip_csv_filepath": null,
    "vstab_airfoil_source": "naca_4",
    "vstab_root_naca_code": "0012",
    "vstab_tip_naca_code": "0008",
    "vstab_root_csv_filepath": null,
    "vstab_tip_csv_filepath": null
  }
}
