{
  "sample_idx": 25469,
  "seed": 20286089,
  "family": "short_fuselage_wide",
  "adv": {
    "tail_type": "conv_tail",
    "length": 902.0,
    "max_width": 163.92,
    "max_height": 88.61,
    "wingspan": 1654.0,
    "wing_position": 0.581,
    "wing_height_ratio": 0.511,
    "tail_position": 0.896,
    "design_name": "standard",
    "wall_thickness": 7.16,
    "end_cap_percent": 0.077,
    "aspect_ratio": 8.42,
    "taper": 0.386,
    "sweep": 18.72,
    "dihedral": 0.51,
    "twist": 2.4,
    "root_incidence": 0.97,
    "airfoil_source": "naca_4",
    "root_naca_code": "2412",
    "tip_naca_code": "2412",
    "root_csv_filepath": null,
    "tip_csv_filepath": null,
    "v_tail_angle": 0.0,
    "hstab_semispan": 277.0,
    "hstab_aspect_ratio": 3.67,
    "hstab_taper": 0.516,
    "hstab_sweep": 16.74,
    "hstab_dihedral": 2.68,
    "hstab_root_incidence": -3.25,
    "hstab_airfoil_source": "naca_4",
    "hstab_root_naca_code": "0012",
    "hstab_tip_naca_code": "0008",
    "hstab_root_csv_filepath": null,
    "hstab_tip_csv_filepath": null,
    "vstab_height": 130.98,
    "vstab_aspect_ratio": 1.84,
    "vstab_taper": 0.42,
    "vstab_sweep": 21.53,
    "vstab_airfoil_source": "naca_4",
    "vstab_root_naca_code": "0012",
    "vstab_tip_naca_code": "0008",
    "vstab_root_csv_filepath": null,
    "vstab_tip_csv_filepath": null
  }
}
