{
  "sample_idx": 34798,
  "seed": 20295418,
  "family": "conv_tail_wide",
  "adv": {
    "tail_type": "conv_tail",
    "length": 1390.0,
    "max_width": 121.49,
    "max_height": 129.04,
    "wingspan": 1300.0,
    "wing_position": 0.435,
    "wing_height_ratio": 0.422,
    "tail_position": 0.885,
    "design_name": "racing",
    "wall_thickness": 5.25,
    "end_cap_percent": 0.068,
    "aspect_ratio": 8.85,
    "taper": 0.526,
    "sweep": 22.11,
    "dihedral": 2.98,
    "twist": 1.19,
    "root_incidence": 3.94,
    "airfoil_source": "naca_4",
    "root_naca_code": "2412",
    "tip_naca_code": "0009",
    "root_csv_filepath": null,
    "tip_csv_filepath": null,
    "v_tail_angle": 0.0,
    "hstab_semispan": 337.0,
    "hstab_aspect_ratio": 4.99,
    "hstab_taper": 0.438,
    "hstab_sweep": 27.49,
    "hstab_dihedral": 5.15,
    "hstab_root_incidence": 0.33,
    "hstab_airfoil_source": "naca_4",
    "hstab_root_naca_code": "0012",
    "hstab_tip_naca_code": "0008",
    "hstab_root_csv_filepath": null,
    "hstab_tip_csv_filepath": null,
    "vstab_height": 192.13,
    "vstab_aspect_ratio": 2.05,
    "vstab_taper": 0.59,
    "vstab_sweep": 38.36,
    "vstab_airfoil_source": "naca_4",
    "vstab_root_naca_code": "0012",
    "vstab_tip_naca_code": "0008",
    "vstab_root_csv_filepath": null,
    "vstab_tip_csv_filepath": null
  }
}
