{
  "sample_idx": 35923,
  "seed": 20296543,
  "family": "forward_tail_wide",
  "adv": {
    "tail_type": "conv_tail",
    "tail_position": 0.843,
    "length": 833.0,
    "max_width": 154.45,
    "max_height": 82.16,
    "wingspan": 1733.0,
    "wing_position": 0.448,
    "wing_height_ratio": 0.538,
    "design_name": "blended",
    "wall_thickness": 5.57,
    "end_cap_percent": 0.053,
    "aspect_ratio": 6.23,
    "taper": 0.378,
    "sweep": 19.79,
    "dihedral": 1.53,
    "twist": 0.42,
    "root_incidence": -0.66,
    "airfoil_source": "naca_4",
    "root_naca_code": "2412",
    "tip_naca_code": "2412",
    "root_csv_filepath": null,
    "tip_csv_filepath": null,
    "v_tail_angle": 0.0,
    "hstab_semispan": 341.0,
    "hstab_aspect_ratio": 4.92,
    "hstab_taper": 0.448,
    "hstab_sweep": 28.02,
    "hstab_dihedral": 7.76,
    "hstab_root_incidence": -2.39,
    "hstab_airfoil_source": "naca_4",
    "hstab_root_naca_code": "0012",
    "hstab_tip_naca_code": "0008",
    "hstab_root_csv_filepath": null,
    "hstab_tip_csv_filepath": null,
    "vstab_height": 173.66,
    "vstab_aspect_ratio": 1.83,
    "vstab_taper": 0.47,
    "vstab_sweep": 38.95,
    "vstab_airfoil_source": "naca_4",
    "vstab_root_naca_code": "0012",
    "vstab_tip_naca_code": "0008",
    "vstab_root_csv_filepath": null,
    "vstab_tip_csv_filepath": null
  }
}
