{
  "sample_idx": 36288,
  "seed": 20296908,
  "family": "low_ar_chord_wide",
  "adv": {
    "tail_type": "conv_tail",
    "aspect_ratio": 6.27,
    "length": 1125.0,
    "max_width": 187.31,
    "max_height": 129.86,
    "wingspan": 1348.0,
    "wing_position": 0.5,
    "wing_height_ratio": 0.39,
    "tail_position": 0.95,
    "design_name": "simple",
    "wall_thickness": 7.4,
    "end_cap_percent": 0.053,
    "taper": 0.527,
    "sweep": 26.24,
    "dihedral": 0.92,
    "twist": 3.56,
    "root_incidence": 1.19,
    "airfoil_source": "naca_4",
    "root_naca_code": "2410",
    "tip_naca_code": "2412",
    "root_csv_filepath": null,
    "tip_csv_filepath": null,
    "v_tail_angle": 0.0,
    "hstab_semispan": 337.0,
    "hstab_aspect_ratio": 3.05,
    "hstab_taper": 0.377,
    "hstab_sweep": 22.67,
    "hstab_dihedral": 1.04,
    "hstab_root_incidence": -4.18,
    "hstab_airfoil_source": "naca_4",
    "hstab_root_naca_code": "0012",
    "hstab_tip_naca_code": "0008",
    "hstab_root_csv_filepath": null,
    "hstab_tip_csv_filepath": null,
    "vstab_height": 130.93,
    "vstab_aspect_ratio": 2.0,
    "vstab_taper": 0.45,
    "vstab_sweep": 20.03,
    "vstab_airfoil_source": "naca_4",
    "vstab_root_naca_code": "0012",
    "vstab_tip_naca_code": "0008",
    "vstab_root_csv_filepath": null,
    "vstab_tip_csv_filepath": null
  }
}
