{
  "sample_idx": 38059,
  "seed": 20298679,
  "family": "aft_wing_short_fuse",
  "adv": {
    "tail_type": "conv_tail",
    "wing_position": 0.62,
    "length": 873.0,
    "max_width": 125.63,
    "max_height": 115.0,
    "wingspan": 1973.0,
    "wing_height_ratio": 0.62,
    "tail_position": 0.888,
    "design_name": "standard",
    "wall_thickness": 3.25,
    "end_cap_percent": 0.046,
    "aspect_ratio": 7.1,
    "taper": 0.367,
    "sweep": 22.05,
    "dihedral": 8.55,
    "twist": 2.57,
    "root_incidence": 4.56,
    "airfoil_source": "naca_4",
    "root_naca_code": "2410",
    "tip_naca_code": "2408",
    "root_csv_filepath": null,
    "tip_csv_filepath": null,
    "v_tail_angle": 0.0,
    "hstab_semispan": 211.0,
    "hstab_aspect_ratio": 4.35,
    "hstab_taper": 0.475,
    "hstab_sweep": 21.35,
    "hstab_dihedral": 2.76,
    "hstab_root_incidence": -1.33,
    "hstab_airfoil_source": "naca_4",
    "hstab_root_naca_code": "0012",
    "hstab_tip_naca_code": "0008",
    "hstab_root_csv_filepath": null,
    "hstab_tip_csv_filepath": null,
    "vstab_height": 113.08,
    "vstab_aspect_ratio": 1.76,
    "vstab_taper": 0.43,
    "vstab_sweep": 20.77,
    "vstab_airfoil_source": "naca_4",
    "vstab_root_naca_code": "0012",
    "vstab_tip_naca_code": "0008",
    "vstab_root_csv_filepath": null,
    "vstab_tip_csv_filepath": null
  }
}
