{
  "sample_idx": 39174,
  "seed": 20299794,
  "family": "extreme_forward_tail_wide",
  "adv": {
    "tail_type": "conv_tail",
    "tail_position": 0.814,
    "length": 857.0,
    "max_width": 169.31,
    "max_height": 131.76,
    "wingspan": 1209.0,
    "wing_position": 0.457,
    "wing_height_ratio": 0.389,
    "design_name": "simple",
    "wall_thickness": 7.4,
    "end_cap_percent": 0.064,
    "aspect_ratio": 10.02,
    "taper": 0.401,
    "sweep": 18.83,
    "dihedral": 4.96,
    "twist": 2.21,
    "root_incidence": 2.0,
    "airfoil_source": "naca_4",
    "root_naca_code": "0012",
    "tip_naca_code": "0009",
    "root_csv_filepath": null,
    "tip_csv_filepath": null,
    "v_tail_angle": 0.0,
    "hstab_semispan": 339.0,
    "hstab_aspect_ratio": 4.31,
    "hstab_taper": 0.506,
    "hstab_sweep": 19.93,
    "hstab_dihedral": 6.81,
    "hstab_root_incidence": -4.47,
    "hstab_airfoil_source": "naca_4",
    "hstab_root_naca_code": "0012",
    "hstab_tip_naca_code": "0008",
    "hstab_root_csv_filepath": null,
    "hstab_tip_csv_filepath": null,
    "vstab_height": 113.44,
    "vstab_aspect_ratio": 1.93,
    "vstab_taper": 0.61,
    "vstab_sweep": 18.86,
    "vstab_airfoil_source": "naca_4",
    "vstab_root_naca_code": "0012",
    "vstab_tip_naca_code": "0008",
    "vstab_root_csv_filepath": null,
    "vstab_tip_csv_filepath": null
  }
}
