{
  "sample_idx": 39496,
  "seed": 20300116,
  "family": "safe_long_forward",
  "adv": {
    "tail_type": "conv_tail",
    "wing_position": 0.48,
    "tail_position": 0.928,
    "length": 1259.0,
    "max_width": 183.98,
    "max_height": 106.07,
    "wingspan": 1664.0,
    "wing_height_ratio": 0.413,
    "design_name": "transport",
    "wall_thickness": 4.59,
    "end_cap_percent": 0.077,
    "aspect_ratio": 8.15,
    "taper": 0.443,
    "sweep": 26.16,
    "dihedral": 9.21,
    "twist": 2.15,
    "root_incidence": 0.41,
    "airfoil_source": "naca_4",
    "root_naca_code": "2412",
    "tip_naca_code": "2408",
    "root_csv_filepath": null,
    "tip_csv_filepath": null,
    "v_tail_angle": 0.0,
    "hstab_semispan": 333.0,
    "hstab_aspect_ratio": 3.21,
    "hstab_taper": 0.53,
    "hstab_sweep": 18.48,
    "hstab_dihedral": 2.21,
    "hstab_root_incidence": 1.54,
    "hstab_airfoil_source": "naca_4",
    "hstab_root_naca_code": "0012",
    "hstab_tip_naca_code": "0008",
    "hstab_root_csv_filepath": null,
    "hstab_tip_csv_filepath": null,
    "vstab_height": 174.61,
    "vstab_aspect_ratio": 1.56,
    "vstab_taper": 0.41,
    "vstab_sweep": 41.16,
    "vstab_airfoil_source": "naca_4",
    "vstab_root_naca_code": "0012",
    "vstab_tip_naca_code": "0008",
    "vstab_root_csv_filepath": null,
    "vstab_tip_csv_filepath": null
  }
}
