{
  "sample_idx": 42138,
  "seed": 20302758,
  "family": "large_aircraft",
  "adv": {
    "tail_type": "conv_tail",
    "length": 1200.0,
    "wingspan": 1800.0,
    "max_width": 187.18,
    "max_height": 114.04,
    "hstab_semispan": 300.0,
    "wing_position": 0.425,
    "wing_height_ratio": 0.6,
    "tail_position": 0.961,
    "design_name": "transport",
    "wall_thickness": 6.17,
    "end_cap_percent": 0.065,
    "aspect_ratio": 10.07,
    "taper": 0.506,
    "sweep": 25.32,
    "dihedral": 3.91,
    "twist": 0.02,
    "root_incidence": -2.92,
    "airfoil_source": "naca_4",
    "root_naca_code": "2412",
    "tip_naca_code": "2412",
    "root_csv_filepath": null,
    "tip_csv_filepath": null,
    "v_tail_angle": 0.0,
    "hstab_aspect_ratio": 3.66,
    "hstab_taper": 0.497,
    "hstab_sweep": 15.4,
    "hstab_dihedral": 7.77,
    "hstab_root_incidence": -2.48,
    "hstab_airfoil_source": "naca_4",
    "hstab_root_naca_code": "0012",
    "hstab_tip_naca_code": "0008",
    "hstab_root_csv_filepath": null,
    "hstab_tip_csv_filepath": null,
    "vstab_height": 139.4,
    "vstab_aspect_ratio": 2.13,
    "vstab_taper": 0.4,
    "vstab_sweep": 40.68,
    "vstab_airfoil_source": "naca_4",
    "vstab_root_naca_code": "0012",
    "vstab_tip_naca_code": "0008",
    "vstab_root_csv_filepath": null,
    "vstab_tip_csv_filepath": null
  }
}
