{
  "sample_idx": 46897,
  "seed": 20307517,
  "family": "extreme_wide_frontier",
  "adv": {
    "wing_position": 0.677,
    "tail_position": 0.881,
    "length": 1420.0,
    "wingspan": 1565.0,
    "aspect_ratio": 10.41,
    "taper": 0.675,
    "sweep": 7.67,
    "dihedral": 1.69,
    "twist": 0.33,
    "root_incidence": 0.71,
    "wing_height_ratio": 0.699,
    "max_width": 168.33,
    "max_height": 60.68,
    "wall_thickness": 10.69,
    "end_cap_percent": 0.071,
    "hstab_semispan": 262.0,
    "hstab_aspect_ratio": 3.12,
    "hstab_taper": 0.514,
    "hstab_sweep": 30.5,
    "hstab_dihedral": 5.58,
    "hstab_root_incidence": 0.93,
    "vstab_height": 130.0,
    "vstab_aspect_ratio": 1.02,
    "vstab_taper": 0.533,
    "vstab_sweep": 36.5,
    "design_name": "blended",
    "airfoil_source": "naca_4",
    "root_naca_code": "0012",
    "tip_naca_code": "2412",
    "root_csv_filepath": null,
    "tip_csv_filepath": null,
    "tail_type": "v_tail",
    "v_tail_angle": 118.4,
    "hstab_airfoil_source": "naca_4",
    "hstab_root_naca_code": "0012",
    "hstab_tip_naca_code": "0008",
    "hstab_root_csv_filepath": null,
    "hstab_tip_csv_filepath": null,
    "vstab_airfoil_source": "naca_4",
    "vstab_root_naca_code": "0012",
    "vstab_tip_naca_code": "0008",
    "vstab_root_csv_filepath": null,
    "vstab_tip_csv_filepath": null
  }
}
