{
  "sample_idx": 47311,
  "seed": 20307931,
  "family": "wide_unconditioned",
  "adv": {
    "length": 1081.0,
    "max_width": 147.11,
    "max_height": 127.22,
    "wingspan": 1969.0,
    "wing_position": 0.459,
    "wing_height_ratio": 0.618,
    "tail_position": 0.877,
    "design_name": "standard",
    "wall_thickness": 7.13,
    "end_cap_percent": 0.041,
    "aspect_ratio": 6.43,
    "taper": 0.355,
    "sweep": 21.81,
    "dihedral": 2.39,
    "twist": 1.73,
    "root_incidence": 0.63,
    "airfoil_source": "naca_4",
    "root_naca_code": "2410",
    "tip_naca_code": "2412",
    "root_csv_filepath": null,
    "tip_csv_filepath": null,
    "tail_type": "v_tail",
    "v_tail_angle": 111.6,
    "hstab_semispan": 281.0,
    "hstab_aspect_ratio": 3.54,
    "hstab_taper": 0.366,
    "hstab_sweep": 17.86,
    "hstab_dihedral": 7.32,
    "hstab_root_incidence": -1.48,
    "hstab_airfoil_source": "naca_4",
    "hstab_root_naca_code": "0012",
    "hstab_tip_naca_code": "0008",
    "hstab_root_csv_filepath": null,
    "hstab_tip_csv_filepath": null,
    "vstab_height": 146.15,
    "vstab_aspect_ratio": 1.89,
    "vstab_taper": 0.37,
    "vstab_sweep": 39.68,
    "vstab_airfoil_source": "naca_4",
    "vstab_root_naca_code": "0012",
    "vstab_tip_naca_code": "0008",
    "vstab_root_csv_filepath": null,
    "vstab_tip_csv_filepath": null
  }
}
