{
  "sample_idx": 49902,
  "seed": 20310522,
  "family": "forward_tail_large_hstab",
  "adv": {
    "tail_type": "conv_tail",
    "tail_position": 0.787,
    "hstab_semispan": 308.0,
    "length": 1245.0,
    "max_width": 133.93,
    "max_height": 107.31,
    "wingspan": 1694.0,
    "wing_position": 0.544,
    "wing_height_ratio": 0.353,
    "design_name": "racing",
    "wall_thickness": 6.68,
    "end_cap_percent": 0.062,
    "aspect_ratio": 6.67,
    "taper": 0.487,
    "sweep": 18.96,
    "dihedral": 9.05,
    "twist": 0.91,
    "root_incidence": -2.09,
    "airfoil_source": "naca_4",
    "root_naca_code": "0012",
    "tip_naca_code": "2412",
    "root_csv_filepath": null,
    "tip_csv_filepath": null,
    "v_tail_angle": 0.0,
    "hstab_aspect_ratio": 4.07,
    "hstab_taper": 0.365,
    "hstab_sweep": 16.9,
    "hstab_dihedral": 2.75,
    "hstab_root_incidence": -5.84,
    "hstab_airfoil_source": "naca_4",
    "hstab_root_naca_code": "0012",
    "hstab_tip_naca_code": "0008",
    "hstab_root_csv_filepath": null,
    "hstab_tip_csv_filepath": null,
    "vstab_height": 190.95,
    "vstab_aspect_ratio": 1.77,
    "vstab_taper": 0.63,
    "vstab_sweep": 21.42,
    "vstab_airfoil_source": "naca_4",
    "vstab_root_naca_code": "0012",
    "vstab_tip_naca_code": "0008",
    "vstab_root_csv_filepath": null,
    "vstab_tip_csv_filepath": null
  }
}
