{
  "sample_idx": 51078,
  "seed": 20311698,
  "family": "large_hstab_wide",
  "adv": {
    "tail_type": "conv_tail",
    "hstab_semispan": 338.0,
    "hstab_aspect_ratio": 3.29,
    "length": 821.0,
    "max_width": 177.47,
    "max_height": 108.7,
    "wingspan": 1912.0,
    "wing_position": 0.603,
    "wing_height_ratio": 0.58,
    "tail_position": 0.881,
    "design_name": "standard",
    "wall_thickness": 7.65,
    "end_cap_percent": 0.055,
    "aspect_ratio": 10.4,
    "taper": 0.439,
    "sweep": 25.42,
    "dihedral": 8.72,
    "twist": 2.86,
    "root_incidence": 4.14,
    "airfoil_source": "naca_4",
    "root_naca_code": "0012",
    "tip_naca_code": "0009",
    "root_csv_filepath": null,
    "tip_csv_filepath": null,
    "v_tail_angle": 0.0,
    "hstab_taper": 0.426,
    "hstab_sweep": 16.38,
    "hstab_dihedral": 0.34,
    "hstab_root_incidence": -0.29,
    "hstab_airfoil_source": "naca_4",
    "hstab_root_naca_code": "0012",
    "hstab_tip_naca_code": "0008",
    "hstab_root_csv_filepath": null,
    "hstab_tip_csv_filepath": null,
    "vstab_height": 205.3,
    "vstab_aspect_ratio": 1.67,
    "vstab_taper": 0.38,
    "vstab_sweep": 33.8,
    "vstab_airfoil_source": "naca_4",
    "vstab_root_naca_code": "0012",
    "vstab_tip_naca_code": "0008",
    "vstab_root_csv_filepath": null,
    "vstab_tip_csv_filepath": null
  }
}
