{
  "sample_idx": 51928,
  "seed": 20312548,
  "family": "forward_tail_wide",
  "adv": {
    "tail_type": "conv_tail",
    "tail_position": 0.852,
    "length": 1280.0,
    "max_width": 189.19,
    "max_height": 77.79,
    "wingspan": 1924.0,
    "wing_position": 0.402,
    "wing_height_ratio": 0.521,
    "design_name": "simple",
    "wall_thickness": 6.97,
    "end_cap_percent": 0.036,
    "aspect_ratio": 8.57,
    "taper": 0.487,
    "sweep": 26.64,
    "dihedral": 1.88,
    "twist": 2.59,
    "root_incidence": 2.83,
    "airfoil_source": "naca_4",
    "root_naca_code": "2412",
    "tip_naca_code": "2412",
    "root_csv_filepath": null,
    "tip_csv_filepath": null,
    "v_tail_angle": 0.0,
    "hstab_semispan": 338.0,
    "hstab_aspect_ratio": 3.18,
    "hstab_taper": 0.353,
    "hstab_sweep": 25.24,
    "hstab_dihedral": 2.21,
    "hstab_root_incidence": -2.19,
    "hstab_airfoil_source": "naca_4",
    "hstab_root_naca_code": "0012",
    "hstab_tip_naca_code": "0008",
    "hstab_root_csv_filepath": null,
    "hstab_tip_csv_filepath": null,
    "vstab_height": 207.06,
    "vstab_aspect_ratio": 1.14,
    "vstab_taper": 0.52,
    "vstab_sweep": 32.07,
    "vstab_airfoil_source": "naca_4",
    "vstab_root_naca_code": "0012",
    "vstab_tip_naca_code": "0008",
    "vstab_root_csv_filepath": null,
    "vstab_tip_csv_filepath": null
  }
}
