{
  "sample_idx": 54546,
  "seed": 20315166,
  "family": "extreme_forward_tail_wide",
  "adv": {
    "tail_type": "conv_tail",
    "tail_position": 0.81,
    "length": 1007.0,
    "max_width": 136.72,
    "max_height": 135.65,
    "wingspan": 1786.0,
    "wing_position": 0.601,
    "wing_height_ratio": 0.62,
    "design_name": "standard",
    "wall_thickness": 5.03,
    "end_cap_percent": 0.061,
    "aspect_ratio": 9.71,
    "taper": 0.424,
    "sweep": 24.04,
    "dihedral": 4.22,
    "twist": 2.0,
    "root_incidence": 0.18,
    "airfoil_source": "naca_4",
    "root_naca_code": "0012",
    "tip_naca_code": "2412",
    "root_csv_filepath": null,
    "tip_csv_filepath": null,
    "v_tail_angle": 0.0,
    "hstab_semispan": 318.0,
    "hstab_aspect_ratio": 4.58,
    "hstab_taper": 0.432,
    "hstab_sweep": 26.8,
    "hstab_dihedral": 6.86,
    "hstab_root_incidence": 0.63,
    "hstab_airfoil_source": "naca_4",
    "hstab_root_naca_code": "0012",
    "hstab_tip_naca_code": "0008",
    "hstab_root_csv_filepath": null,
    "hstab_tip_csv_filepath": null,
    "vstab_height": 117.52,
    "vstab_aspect_ratio": 1.61,
    "vstab_taper": 0.55,
    "vstab_sweep": 41.73,
    "vstab_airfoil_source": "naca_4",
    "vstab_root_naca_code": "0012",
    "vstab_tip_naca_code": "0008",
    "vstab_root_csv_filepath": null,
    "vstab_tip_csv_filepath": null
  }
}
