{
  "sample_idx": 56061,
  "seed": 20316681,
  "family": "large_hstab_wide",
  "adv": {
    "tail_type": "conv_tail",
    "hstab_semispan": 328.0,
    "hstab_aspect_ratio": 2.56,
    "length": 1288.0,
    "max_width": 176.85,
    "max_height": 86.9,
    "wingspan": 1377.0,
    "wing_position": 0.652,
    "wing_height_ratio": 0.375,
    "tail_position": 0.901,
    "design_name": "blended",
    "wall_thickness": 6.07,
    "end_cap_percent": 0.031,
    "aspect_ratio": 8.14,
    "taper": 0.528,
    "sweep": 27.67,
    "dihedral": 8.23,
    "twist": 2.02,
    "root_incidence": 0.54,
    "airfoil_source": "naca_4",
    "root_naca_code": "2412",
    "tip_naca_code": "2408",
    "root_csv_filepath": null,
    "tip_csv_filepath": null,
    "v_tail_angle": 0.0,
    "hstab_taper": 0.358,
    "hstab_sweep": 28.53,
    "hstab_dihedral": 6.66,
    "hstab_root_incidence": -5.23,
    "hstab_airfoil_source": "naca_4",
    "hstab_root_naca_code": "0012",
    "hstab_tip_naca_code": "0008",
    "hstab_root_csv_filepath": null,
    "hstab_tip_csv_filepath": null,
    "vstab_height": 112.06,
    "vstab_aspect_ratio": 1.72,
    "vstab_taper": 0.65,
    "vstab_sweep": 22.84,
    "vstab_airfoil_source": "naca_4",
    "vstab_root_naca_code": "0012",
    "vstab_tip_naca_code": "0008",
    "vstab_root_csv_filepath": null,
    "vstab_tip_csv_filepath": null
  }
}
