{
  "sample_idx": 58668,
  "seed": 20319288,
  "family": "aft_wing_wide",
  "adv": {
    "tail_type": "conv_tail",
    "wing_position": 0.6,
    "length": 1372.0,
    "max_width": 156.63,
    "max_height": 114.68,
    "wingspan": 1936.0,
    "wing_height_ratio": 0.396,
    "tail_position": 0.857,
    "design_name": "transport",
    "wall_thickness": 4.05,
    "end_cap_percent": 0.058,
    "aspect_ratio": 9.32,
    "taper": 0.542,
    "sweep": 16.03,
    "dihedral": 5.27,
    "twist": 0.34,
    "root_incidence": 4.52,
    "airfoil_source": "naca_4",
    "root_naca_code": "0012",
    "tip_naca_code": "0009",
    "root_csv_filepath": null,
    "tip_csv_filepath": null,
    "v_tail_angle": 0.0,
    "hstab_semispan": 323.0,
    "hstab_aspect_ratio": 3.48,
    "hstab_taper": 0.468,
    "hstab_sweep": 23.29,
    "hstab_dihedral": 6.87,
    "hstab_root_incidence": -2.35,
    "hstab_airfoil_source": "naca_4",
    "hstab_root_naca_code": "0012",
    "hstab_tip_naca_code": "0008",
    "hstab_root_csv_filepath": null,
    "hstab_tip_csv_filepath": null,
    "vstab_height": 187.28,
    "vstab_aspect_ratio": 1.79,
    "vstab_taper": 0.53,
    "vstab_sweep": 28.56,
    "vstab_airfoil_source": "naca_4",
    "vstab_root_naca_code": "0012",
    "vstab_tip_naca_code": "0008",
    "vstab_root_csv_filepath": null,
    "vstab_tip_csv_filepath": null
  }
}
