{
  "sample_idx": 67785,
  "seed": 20328405,
  "family": "large_hstab_wide",
  "adv": {
    "tail_type": "conv_tail",
    "hstab_semispan": 336.0,
    "hstab_aspect_ratio": 2.58,
    "length": 1008.0,
    "max_width": 147.97,
    "max_height": 80.88,
    "wingspan": 1654.0,
    "wing_position": 0.524,
    "wing_height_ratio": 0.644,
    "tail_position": 0.941,
    "design_name": "blended",
    "wall_thickness": 6.66,
    "end_cap_percent": 0.079,
    "aspect_ratio": 7.28,
    "taper": 0.494,
    "sweep": 20.96,
    "dihedral": 8.25,
    "twist": 1.33,
    "root_incidence": -1.01,
    "airfoil_source": "naca_4",
    "root_naca_code": "2410",
    "tip_naca_code": "2408",
    "root_csv_filepath": null,
    "tip_csv_filepath": null,
    "v_tail_angle": 0.0,
    "hstab_taper": 0.491,
    "hstab_sweep": 20.25,
    "hstab_dihedral": 7.61,
    "hstab_root_incidence": -3.33,
    "hstab_airfoil_source": "naca_4",
    "hstab_root_naca_code": "0012",
    "hstab_tip_naca_code": "0008",
    "hstab_root_csv_filepath": null,
    "hstab_tip_csv_filepath": null,
    "vstab_height": 194.03,
    "vstab_aspect_ratio": 2.14,
    "vstab_taper": 0.4,
    "vstab_sweep": 39.52,
    "vstab_airfoil_source": "naca_4",
    "vstab_root_naca_code": "0012",
    "vstab_tip_naca_code": "0008",
    "vstab_root_csv_filepath": null,
    "vstab_tip_csv_filepath": null
  }
}
