{
  "sample_idx": 72001,
  "seed": 20332621,
  "family": "wide_categorical_coverage",
  "adv": {
    "tail_type": "conv_tail",
    "design_name": "simple",
    "root_naca_code": "0012",
    "tip_naca_code": "2408",
    "length": 919.0,
    "max_width": 172.3,
    "max_height": 86.37,
    "wingspan": 1201.0,
    "wing_position": 0.522,
    "wing_height_ratio": 0.554,
    "tail_position": 0.895,
    "wall_thickness": 6.2,
    "end_cap_percent": 0.056,
    "aspect_ratio": 8.86,
    "taper": 0.431,
    "sweep": 16.85,
    "dihedral": 2.53,
    "twist": 1.47,
    "root_incidence": -1.32,
    "airfoil_source": "naca_4",
    "root_csv_filepath": null,
    "tip_csv_filepath": null,
    "v_tail_angle": 0.0,
    "hstab_semispan": 217.0,
    "hstab_aspect_ratio": 4.73,
    "hstab_taper": 0.377,
    "hstab_sweep": 25.98,
    "hstab_dihedral": 3.52,
    "hstab_root_incidence": -5.8,
    "hstab_airfoil_source": "naca_4",
    "hstab_root_naca_code": "0012",
    "hstab_tip_naca_code": "0008",
    "hstab_root_csv_filepath": null,
    "hstab_tip_csv_filepath": null,
    "vstab_height": 212.12,
    "vstab_aspect_ratio": 2.06,
    "vstab_taper": 0.5,
    "vstab_sweep": 30.61,
    "vstab_airfoil_source": "naca_4",
    "vstab_root_naca_code": "0012",
    "vstab_tip_naca_code": "0008",
    "vstab_root_csv_filepath": null,
    "vstab_tip_csv_filepath": null
  }
}
