{
  "sample_idx": 73297,
  "seed": 20333917,
  "family": "wide_categorical_coverage",
  "adv": {
    "tail_type": "conv_tail",
    "design_name": "transport",
    "root_naca_code": "0012",
    "tip_naca_code": "0009",
    "length": 1040.0,
    "max_width": 100.6,
    "max_height": 109.29,
    "wingspan": 1516.0,
    "wing_position": 0.546,
    "wing_height_ratio": 0.544,
    "tail_position": 0.959,
    "wall_thickness": 6.14,
    "end_cap_percent": 0.043,
    "aspect_ratio": 10.64,
    "taper": 0.539,
    "sweep": 25.66,
    "dihedral": 5.77,
    "twist": 3.32,
    "root_incidence": -1.07,
    "airfoil_source": "naca_4",
    "root_csv_filepath": null,
    "tip_csv_filepath": null,
    "v_tail_angle": 0.0,
    "hstab_semispan": 202.0,
    "hstab_aspect_ratio": 3.45,
    "hstab_taper": 0.501,
    "hstab_sweep": 18.32,
    "hstab_dihedral": 3.11,
    "hstab_root_incidence": -1.21,
    "hstab_airfoil_source": "naca_4",
    "hstab_root_naca_code": "0012",
    "hstab_tip_naca_code": "0008",
    "hstab_root_csv_filepath": null,
    "hstab_tip_csv_filepath": null,
    "vstab_height": 213.16,
    "vstab_aspect_ratio": 1.37,
    "vstab_taper": 0.51,
    "vstab_sweep": 25.32,
    "vstab_airfoil_source": "naca_4",
    "vstab_root_naca_code": "0012",
    "vstab_tip_naca_code": "0008",
    "vstab_root_csv_filepath": null,
    "vstab_tip_csv_filepath": null
  }
}
