{
  "sample_idx": 79341,
  "seed": 20339961,
  "family": "compact_aircraft",
  "adv": {
    "tail_type": "conv_tail",
    "length": 804.0,
    "wingspan": 1487.0,
    "max_width": 105.89,
    "max_height": 88.52,
    "wing_position": 0.581,
    "wing_height_ratio": 0.358,
    "tail_position": 0.878,
    "design_name": "blended",
    "wall_thickness": 5.76,
    "end_cap_percent": 0.034,
    "aspect_ratio": 10.67,
    "taper": 0.401,
    "sweep": 17.18,
    "dihedral": 0.99,
    "twist": 2.93,
    "root_incidence": 0.85,
    "airfoil_source": "naca_4",
    "root_naca_code": "2410",
    "tip_naca_code": "2408",
    "root_csv_filepath": null,
    "tip_csv_filepath": null,
    "v_tail_angle": 0.0,
    "hstab_semispan": 303.0,
    "hstab_aspect_ratio": 4.65,
    "hstab_taper": 0.398,
    "hstab_sweep": 21.17,
    "hstab_dihedral": 7.45,
    "hstab_root_incidence": 1.54,
    "hstab_airfoil_source": "naca_4",
    "hstab_root_naca_code": "0012",
    "hstab_tip_naca_code": "0008",
    "hstab_root_csv_filepath": null,
    "hstab_tip_csv_filepath": null,
    "vstab_height": 166.66,
    "vstab_aspect_ratio": 2.1,
    "vstab_taper": 0.36,
    "vstab_sweep": 18.06,
    "vstab_airfoil_source": "naca_4",
    "vstab_root_naca_code": "0012",
    "vstab_tip_naca_code": "0008",
    "vstab_root_csv_filepath": null,
    "vstab_tip_csv_filepath": null
  }
}
