{
  "sample_idx": 79519,
  "seed": 20340139,
  "family": "moderate_spacing_triad",
  "adv": {
    "tail_type": "conv_tail",
    "wing_position": 0.589,
    "tail_position": 0.846,
    "length": 951.0,
    "max_width": 110.76,
    "max_height": 97.02,
    "wingspan": 1812.0,
    "wing_height_ratio": 0.518,
    "design_name": "simple",
    "wall_thickness": 6.31,
    "end_cap_percent": 0.038,
    "aspect_ratio": 7.15,
    "taper": 0.457,
    "sweep": 22.25,
    "dihedral": 3.17,
    "twist": 3.28,
    "root_incidence": 2.41,
    "airfoil_source": "naca_4",
    "root_naca_code": "2412",
    "tip_naca_code": "0009",
    "root_csv_filepath": null,
    "tip_csv_filepath": null,
    "v_tail_angle": 0.0,
    "hstab_semispan": 286.0,
    "hstab_aspect_ratio": 3.99,
    "hstab_taper": 0.425,
    "hstab_sweep": 15.04,
    "hstab_dihedral": 3.88,
    "hstab_root_incidence": 0.29,
    "hstab_airfoil_source": "naca_4",
    "hstab_root_naca_code": "0012",
    "hstab_tip_naca_code": "0008",
    "hstab_root_csv_filepath": null,
    "hstab_tip_csv_filepath": null,
    "vstab_height": 198.04,
    "vstab_aspect_ratio": 1.5,
    "vstab_taper": 0.6,
    "vstab_sweep": 30.82,
    "vstab_airfoil_source": "naca_4",
    "vstab_root_naca_code": "0012",
    "vstab_tip_naca_code": "0008",
    "vstab_root_csv_filepath": null,
    "vstab_tip_csv_filepath": null
  }
}
