{
  "sample_idx": 79534,
  "seed": 20340154,
  "family": "conv_tail_broad",
  "adv": {
    "tail_type": "conv_tail",
    "length": 1070.0,
    "max_width": 108.18,
    "max_height": 129.48,
    "wingspan": 1701.0,
    "wing_position": 0.515,
    "wing_height_ratio": 0.549,
    "tail_position": 0.888,
    "design_name": "racing",
    "wall_thickness": 5.05,
    "end_cap_percent": 0.051,
    "aspect_ratio": 6.89,
    "taper": 0.471,
    "sweep": 19.88,
    "dihedral": 8.19,
    "twist": 2.98,
    "root_incidence": 2.65,
    "airfoil_source": "naca_4",
    "root_naca_code": "2410",
    "tip_naca_code": "0009",
    "root_csv_filepath": null,
    "tip_csv_filepath": null,
    "v_tail_angle": 0.0,
    "hstab_semispan": 283.0,
    "hstab_aspect_ratio": 3.22,
    "hstab_taper": 0.496,
    "hstab_sweep": 16.0,
    "hstab_dihedral": 6.86,
    "hstab_root_incidence": 0.32,
    "hstab_airfoil_source": "naca_4",
    "hstab_root_naca_code": "0012",
    "hstab_tip_naca_code": "0008",
    "hstab_root_csv_filepath": null,
    "hstab_tip_csv_filepath": null,
    "vstab_height": 219.32,
    "vstab_aspect_ratio": 1.25,
    "vstab_taper": 0.4,
    "vstab_sweep": 22.03,
    "vstab_airfoil_source": "naca_4",
    "vstab_root_naca_code": "0012",
    "vstab_tip_naca_code": "0008",
    "vstab_root_csv_filepath": null,
    "vstab_tip_csv_filepath": null
  }
}
