{
  "sample_idx": 90825,
  "seed": 20351445,
  "family": "extreme_wide_frontier",
  "adv": {
    "wing_position": 0.441,
    "tail_position": 0.849,
    "length": 939.0,
    "wingspan": 1570.0,
    "aspect_ratio": 6.93,
    "taper": 0.469,
    "sweep": 22.47,
    "dihedral": 6.75,
    "twist": 0.27,
    "root_incidence": 1.95,
    "wing_height_ratio": 0.544,
    "max_width": 210.9,
    "max_height": 87.02,
    "wall_thickness": 9.95,
    "end_cap_percent": 0.033,
    "hstab_semispan": 417.0,
    "hstab_aspect_ratio": 2.3,
    "hstab_taper": 0.668,
    "hstab_sweep": 38.49,
    "hstab_dihedral": 3.62,
    "hstab_root_incidence": 3.01,
    "vstab_height": 262.0,
    "vstab_aspect_ratio": 1.05,
    "vstab_taper": 0.689,
    "vstab_sweep": 48.94,
    "design_name": "standard",
    "airfoil_source": "naca_4",
    "root_naca_code": "2412",
    "tip_naca_code": "2412",
    "root_csv_filepath": null,
    "tip_csv_filepath": null,
    "tail_type": "v_tail",
    "v_tail_angle": 129.8,
    "hstab_airfoil_source": "naca_4",
    "hstab_root_naca_code": "0012",
    "hstab_tip_naca_code": "0008",
    "hstab_root_csv_filepath": null,
    "hstab_tip_csv_filepath": null,
    "vstab_airfoil_source": "naca_4",
    "vstab_root_naca_code": "0012",
    "vstab_tip_naca_code": "0008",
    "vstab_root_csv_filepath": null,
    "vstab_tip_csv_filepath": null
  }
}
