{
  "sample_idx": 94012,
  "seed": 20354632,
  "family": "forward_tail_aft_wing",
  "adv": {
    "tail_type": "conv_tail",
    "wing_position": 0.603,
    "tail_position": 0.804,
    "length": 1397.0,
    "max_width": 153.47,
    "max_height": 128.33,
    "wingspan": 1380.0,
    "wing_height_ratio": 0.516,
    "design_name": "blended",
    "wall_thickness": 4.67,
    "end_cap_percent": 0.068,
    "aspect_ratio": 9.04,
    "taper": 0.501,
    "sweep": 15.06,
    "dihedral": 2.73,
    "twist": 3.47,
    "root_incidence": 1.84,
    "airfoil_source": "naca_4",
    "root_naca_code": "0012",
    "tip_naca_code": "2412",
    "root_csv_filepath": null,
    "tip_csv_filepath": null,
    "v_tail_angle": 0.0,
    "hstab_semispan": 266.0,
    "hstab_aspect_ratio": 3.34,
    "hstab_taper": 0.369,
    "hstab_sweep": 24.97,
    "hstab_dihedral": 1.27,
    "hstab_root_incidence": -3.49,
    "hstab_airfoil_source": "naca_4",
    "hstab_root_naca_code": "0012",
    "hstab_tip_naca_code": "0008",
    "hstab_root_csv_filepath": null,
    "hstab_tip_csv_filepath": null,
    "vstab_height": 223.85,
    "vstab_aspect_ratio": 1.47,
    "vstab_taper": 0.48,
    "vstab_sweep": 37.35,
    "vstab_airfoil_source": "naca_4",
    "vstab_root_naca_code": "0012",
    "vstab_tip_naca_code": "0008",
    "vstab_root_csv_filepath": null,
    "vstab_tip_csv_filepath": null
  }
}
