{
  "sample_idx": 98915,
  "seed": 20359535,
  "family": "forward_tail_wide",
  "adv": {
    "tail_type": "conv_tail",
    "tail_position": 0.872,
    "length": 1182.0,
    "max_width": 199.91,
    "max_height": 122.23,
    "wingspan": 1965.0,
    "wing_position": 0.618,
    "wing_height_ratio": 0.624,
    "design_name": "simple",
    "wall_thickness": 4.25,
    "end_cap_percent": 0.061,
    "aspect_ratio": 6.26,
    "taper": 0.493,
    "sweep": 20.59,
    "dihedral": 4.31,
    "twist": 3.37,
    "root_incidence": 2.32,
    "airfoil_source": "naca_4",
    "root_naca_code": "2412",
    "tip_naca_code": "0009",
    "root_csv_filepath": null,
    "tip_csv_filepath": null,
    "v_tail_angle": 0.0,
    "hstab_semispan": 323.0,
    "hstab_aspect_ratio": 4.09,
    "hstab_taper": 0.429,
    "hstab_sweep": 21.05,
    "hstab_dihedral": 0.83,
    "hstab_root_incidence": -2.71,
    "hstab_airfoil_source": "naca_4",
    "hstab_root_naca_code": "0012",
    "hstab_tip_naca_code": "0008",
    "hstab_root_csv_filepath": null,
    "hstab_tip_csv_filepath": null,
    "vstab_height": 199.61,
    "vstab_aspect_ratio": 1.38,
    "vstab_taper": 0.47,
    "vstab_sweep": 38.85,
    "vstab_airfoil_source": "naca_4",
    "vstab_root_naca_code": "0012",
    "vstab_tip_naca_code": "0008",
    "vstab_root_csv_filepath": null,
    "vstab_tip_csv_filepath": null
  }
}
